chesstools/__init__.py
chesstools/board.py
chesstools/book.py
chesstools/list.py
chesstools/move.py
chesstools/piece.py
chesstools/timer.py
chesstools/ai/__init__.py
chesstools/ai/brain.py
chesstools/ai/thinker.py
chesstools/ai/transposition.py
chesstools/ai/variation.py
chesstools-0.2.4.12.dist-info/METADATA
chesstools-0.2.4.12.dist-info/WHEEL
chesstools-0.2.4.12.dist-info/entry_points.txt
chesstools-0.2.4.12.dist-info/top_level.txt
chesstools-0.2.4.12.dist-info/RECORD
