Metadata-Version: 2.1
Name: chesstools
Version: 0.2.4.12
Summary: A library of tools for writing chess AI's, as well as servers, clients, and any other software that requires a chess engine.
Home-page: http://www.mariobalibrera.com/mics
Download-URL: http://code.google.com/p/chesstools/downloads/list
Author: Mario Balibrera
Author-email: mario.balibrera@gmail.com
License: MIT License
Classifier: Development Status :: 3 - Alpha
Classifier: Environment :: Console
Classifier: Intended Audience :: Developers
Classifier: License :: OSI Approved :: MIT License
Classifier: Operating System :: OS Independent
Classifier: Programming Language :: Python
Classifier: Topic :: Software Development :: Libraries :: Python Modules
Requires-Dist: databae >=0.1.4.5
